lins_unous/__init__.py
lins_unous/lins_unous.py
lins_unous/lins_unous_tests.py
lins_unous/unous_requests.py
lins_unous/unous_requests_tests.py
lins_unous-2.0.5.100.dist-info/METADATA
lins_unous-2.0.5.100.dist-info/WHEEL
lins_unous-2.0.5.100.dist-info/top_level.txt
lins_unous-2.0.5.100.dist-info/RECORD
