Metadata-Version: 2.1
Name: lins-unous
Version: 2.0.5.100
Summary: Classe para uso da API unous.
Home-page: https://bitbucket.org/grupolinsferrao/pypck-lins_unous/
Author: Nicollas Borges
Author-email: nicollasborges@lojaspompeia.com.br
License: MIT
Platform: UNKNOWN
Requires-Dist: pytz
Requires-Dist: requests
